cloudshell_cli/__init__.py
cloudshell_cli/cli.py
cloudshell_cli/utils.py
cloudshell_cli/app/__init__.py
cloudshell_cli/app/app.py
cloudshell_cli/app/requirements.txt
cloudshell_cli/dockerfiles/Dockerfile
cloudshell_cli/dockerfiles/__init__.py
cloudshell_cli/scripts/__init__.py
cloudshell_cli/scripts/buscar-archivo-s3.sh
cloudshell_cli/scripts/correr-docker-ecr.sh
cloudshell_cli/scripts/crear-y-subir-imagen-ecr.sh
cloudshell_cli/scripts/deploy-ecs.sh
cloudshell_cli/templates/__init__.py
cloudshell_cli/templates/template-ecs.yaml
cloudshell_tools-0.1.4.dist-info/METADATA
cloudshell_tools-0.1.4.dist-info/WHEEL
cloudshell_tools-0.1.4.dist-info/entry_points.txt
cloudshell_tools-0.1.4.dist-info/top_level.txt
cloudshell_tools-0.1.4.dist-info/RECORD
