Metadata-Version: 2.4
Name: cloudshell-tools
Version: 0.1.4
Summary: CLI para automatizar tareas en AWS CloudShell
Author-email: Santiago Rojas <santirojas20@gmail.com>
Project-URL: Homepage, https://gitlab.com/santirojas20/cloudshell-aws
Requires-Dist: click
